lazyclaude/__init__.py
lazyclaude/__main__.py
lazyclaude/_version.py
lazyclaude/app.py
lazyclaude/bindings.py
lazyclaude/themes.py
lazyclaude/keybindings/__init__.py
lazyclaude/mixins/CLAUDE.md
lazyclaude/mixins/__init__.py
lazyclaude/mixins/customization_actions.py
lazyclaude/mixins/filtering.py
lazyclaude/mixins/help.py
lazyclaude/mixins/marketplace.py
lazyclaude/mixins/navigation.py
lazyclaude/models/__init__.py
lazyclaude/models/customization.py
lazyclaude/models/marketplace.py
lazyclaude/models/settings.py
lazyclaude/services/__init__.py
lazyclaude/services/config_path_resolver.py
lazyclaude/services/discovery.py
lazyclaude/services/filesystem_scanner.py
lazyclaude/services/filter.py
lazyclaude/services/gitignore_filter.py
lazyclaude/services/marketplace_loader.py
lazyclaude/services/opener.py
lazyclaude/services/plugin_loader.py
lazyclaude/services/settings.py
lazyclaude/services/writer.py
lazyclaude/services/parsers/__init__.py
lazyclaude/services/parsers/hook.py
lazyclaude/services/parsers/lsp_server.py
lazyclaude/services/parsers/mcp.py
lazyclaude/services/parsers/memory_file.py
lazyclaude/services/parsers/skill.py
lazyclaude/services/parsers/slash_command.py
lazyclaude/services/parsers/subagent.py
lazyclaude/styles/app.tcss
lazyclaude/widgets/__init__.py
lazyclaude/widgets/app_footer.py
lazyclaude/widgets/combined_panel.py
lazyclaude/widgets/delete_confirm.py
lazyclaude/widgets/detail_pane.py
lazyclaude/widgets/filter_input.py
lazyclaude/widgets/level_selector.py
lazyclaude/widgets/marketplace_confirm.py
lazyclaude/widgets/marketplace_modal.py
lazyclaude/widgets/marketplace_source_input.py
lazyclaude/widgets/plugin_confirm.py
lazyclaude/widgets/status_panel.py
lazyclaude/widgets/type_panel.py
lazyclaude/widgets/helpers/__init__.py
lazyclaude/widgets/helpers/rendering.py
lazyclaude-0.12.10.dist-info/METADATA
lazyclaude-0.12.10.dist-info/WHEEL
lazyclaude-0.12.10.dist-info/entry_points.txt
lazyclaude-0.12.10.dist-info/licenses/LICENSE.md
lazyclaude-0.12.10.dist-info/RECORD
